wagtail_storages/__init__.py
wagtail_storages/apps.py
wagtail_storages/backends.py
wagtail_storages/factories.py
wagtail_storages/signal_handlers.py
wagtail_storages/utils.py
wagtail_storages/wagtail_hooks.py
wagtail_storages/management/__init__.py
wagtail_storages/management/commands/__init__.py
wagtail_storages/management/commands/fix_document_acls.py
wagtail_storages-2.0.dist-info/LICENSE
wagtail_storages-2.0.dist-info/METADATA
wagtail_storages-2.0.dist-info/WHEEL
wagtail_storages-2.0.dist-info/top_level.txt
wagtail_storages-2.0.dist-info/RECORD
