Metadata-Version: 2.1
Name: wagtail-storages
Version: 2.0
Summary: Use AWS S3 with private documents in Wagtail.
Home-page: https://github.com/torchbox/wagtail-storages
Author: Torchbox
Author-email: info@torchbox.com
Maintainer: Torchbox
Maintainer-email: info@torchbox.com
License: BSD 3-Clause License
Keywords: wagtail,s3,django,storages,storage
Classifier: Development Status :: 5 - Production/Stable
Classifier: License :: OSI Approved
Classifier: License :: OSI Approved :: BSD License
Classifier: Programming Language :: Python :: 3.10
Classifier: Programming Language :: Python :: 3.11
Classifier: Programming Language :: Python :: 3.12
Classifier: Topic :: Internet :: WWW/HTTP
Classifier: Framework :: Django
Classifier: Framework :: Django :: 4.2
Classifier: Framework :: Django :: 5.0
Classifier: Framework :: Django :: 5.1
Classifier: Framework :: Wagtail
Classifier: Framework :: Wagtail :: 5
Classifier: Framework :: Wagtail :: 6
Requires-Python: >=3.10
License-File: LICENSE
Requires-Dist: Django>=4.2
Requires-Dist: Wagtail>=5.2
Requires-Dist: django-storages[boto3]<2
Provides-Extra: testing
Requires-Dist: coverage==7.5.2; extra == "testing"
Requires-Dist: factory_boy==3.3.0; extra == "testing"
Requires-Dist: moto[s3]<6,>=5; extra == "testing"
Requires-Dist: black==24.4.2; extra == "testing"
Requires-Dist: isort; extra == "testing"
Requires-Dist: flake8; extra == "testing"
